iverilog_basics_ubuntu/verilog-course.v/verilog/02_test_bench/02-1_voter1/voter_self.v
// A voter function evaluates the mode of an array of system outputs, some of which may be erroneous. Based on the assumption that the majority of outputs are not corrupted by any means, this function utilises simple bitwise logic to evaluate the majority bit. 

// Timescale configuration

`timescale 1ns / 1ps

// Configure the module, and its respective input and output ports. Defining
// these within the module block itself assures global usage; these inputs and
// outputs may be invoked remotely in a different file/testbench. By default,
// input and output ports are assigned as 'wires', unless stated otherwise. 
module voter (
	output reg f, 
	input wire a,
	input wire b,
	input wire c
	);

	// Combinational logic defined procedurally must always be embedded
	// within 'always' blocks, with a list of parameters (typically the
	// inputs). 
	always @(a, b, c)
	begin 
		// For sake of simplicity and readability, a 'case'
		// conditional statement was included instead of an if-else
		// statement. This cross-references the value of 'a' with
		// different cases; when a = 1, an 'OR' comparison between 'b'
		// and 'c' is computed, since either 'b' or 'c' (or both) must
		// be high for the mode to be '1'. Conversely, the 'default'
		// case (optional, but included to prevent any floating states)
		// is applicable when a = 0, triggering an 'AND' comparison
		// between 'b' and 'c', since both of these inputs must be
		// high for the mode to equate to '1'.
		case(a)
		
		1:
			f = b | c;
		
		default: 
			f = b & c;
		endcase
	end
endmodule

iverilog_basics_ubuntu/verilog-course.v/verilog/02_test_bench/02-1_voter1/voter_selftb.v
// Testbench for 'voter_self.v'. 

// Configuration of the timescale (identical to the timescale in previous examples)

`timescale 1ns / 1ps

// The testbench is a portless module, i.e. devoid of any input and output ports, since the inputs and outputs configured are reserved solely for simulation purposes. 

module test();

	wire f; 
	reg a, b, c;
	
	// Create an instance of the 'voter_self.v' file via UUT
	// instantiation (Unit Under Test), which is a widely accepted
	// method of pulling input and output ports, alongside an extensive
	// description of the combinational logic from a target file, to be instantiated in this
	// testbench and simulated for prototyping purposes, thereby verifying
	// the functional capabilities of the current RTL design. 
	
	voter uut (.f(f), .a(a), .b(b), .c(c)); // The output and input port variables directly align with one another. 

	// Signal initialisation and simulation control
	// 'initial begin' denotes the commencement of the simulation phase.
	// Data is thereafter dumped periodically into a 'vcd' file for
	// visualisation on gtkwave. 
	
	initial begin
		a = 0;
		b = 0;
		c = 0; // Set all testbench-native variables to zero. 

		// Employing an identical method to previous exercises,
		// utilise $dumpvars to dump simulation data episodically
		// within an newly created file. 

		$dumpfile("voter_tb.vcd"); // Waveform generation. 
		$dumpvars(0, test);

		// Establish the transient simulation range (in nanoseconds)

		#100 $finish;


	end 

	// Configure time interval patterns for variable inversions
	
        always
	    #5 a = ~a;
	always 
	    #10 b = ~b;
	always
	    #20 c = ~c;
endmodule

iverilog_basics_ubuntu/verilog-course.v/verilog/02_test_bench/02-1_voter1/voter_tb.vcd
$date
	Thu Jun 11 00:44:11 2026
$end
$version
	Icarus Verilog
$end
$timescale
	1ps
$end
$scope module test $end
$var wire 1 ! f $end
$var reg 1 " a $end
$var reg 1 # b $end
$var reg 1 $ c $end
$scope module uut $end
$var wire 1 " a $end
$var wire 1 # b $end
$var wire 1 $ c $end
$var reg 1 ! f $end
$upscope $end
$upscope $end
$enddefinitions $end
$comment Show the parameter values. $end
$dumpall
$end
#0
$dumpvars
0$
0#
0"
0!
$end
#5000
1"
#10000
0"
1#
#15000
1!
1"
#20000
0!
0"
0#
1$
#25000
1!
1"
#30000
0"
1#
#35000
1"
#40000
0!
0"
0#
0$
#45000
1"
#50000
0"
1#
#55000
1!
1"
#60000
0!
0"
0#
1$
#65000
1!
1"
#70000
0"
1#
#75000
1"
#80000
0!
0"
0#
0$
#85000
1"
#90000
0"
1#
#95000
1!
1"
#100000
0!
0"
0#
1$
