iverilog_basics_ubuntu/verilog-course.v/verilog/01_intro/01-2_logic_functions/functions_self.v

// Instantiation of a timescale. The first time argument defines the time step
// (i.e. 1ns). The second time argument following the slash defines the
// maximum resolutions depicted on the waveform output. 
`timescale 1ns / 1ps


// Invocation of a module to execute simplistic combinational logic
module logic_function_self ();

   // Initialise two input signals, by representing them as variables 'a' and 'b' via the 'reg' function. These two variables are to be initially fixed at zero, subject to further
   //  variability via a series of operations.  
   reg a = 0, b = 0, c = 0; 

   // In the context of the circuit, the two variables modelled above must be
   // associated with a corresponding output terminal, invoked via the 'wire'
   // function. This function is dependent on the input signals 'a' and 'b'
   // fluctuating. 

   wire f; 

   // Define the relationship between the input signals and the output
   // terminal via a series of operations (AND (&), OR(|), XOR(^) and NOT(~)). 
   
   assign f = (a|b|~c) & (a|~b|c) & (~a|b|c); 

   // Invert the input signal 'a' every 10ns (in accordance with the
   // pre-defined timestep of 1ns). 
   always
      #10 a = ~a; 
   // Invert the input signal 'b every 20ns (in accordance with the
   // pre-defined timestep of 1ns). 
   always
      #20 b = ~b;
   
   always 
      #40 c = ~c;

   initial begin
      // The distinction between '$monitor' and '$display' for printing an
      // output lies in the former passively tracking if the output variable
      // 'f' is altered at any given point during the simulation. '%b'
      // represents an in-line binary-to-string conversion of the inputs and
      // outputs defined earlier, as well as indicating that this identifier
      // must be replaced in order by the parameter arguments that follow (a,b,
      // f).  
      $monitor("a=%b, b=%b, f=%b", a, b, f);

     // '$dumpvars' enables paramater value changes to be recorded into
     // a simulation history file. The first argument of this function indicates the
     // scope of module data extraction ('0' being the most), and the target
     // top-level module within the program. '$dumpfile' defines the exact
     // filename of the output simulation history file, which subsequently can
     // be displayed on gtkwave. 

     $dumpfile("logicfunction_self.vcd");
     $dumpvars(0, logic_function_self);

     // Fix the transient simulation range, via the '$finish' command
     #200 $finish;

   end
endmodule

iverilog_basics_ubuntu/verilog-course.v/verilog/01_intro/01-2_logic_functions/logicfunction_self.vcd
$date
	Wed Jun 10 17:09:10 2026
$end
$version
	Icarus Verilog
$end
$timescale
	1ps
$end
$scope module logic_function_self $end
$var wire 1 ! f $end
$var reg 1 " a $end
$var reg 1 # b $end
$var reg 1 $ c $end
$upscope $end
$enddefinitions $end
$comment Show the parameter values. $end
$dumpall
$end
#0
$dumpvars
0$
0#
0"
1!
$end
#10000
0!
1"
#20000
0!
0"
1#
#30000
1!
1"
#40000
0!
0"
0#
1$
#50000
1!
1"
#60000
0"
1#
#70000
1"
#80000
1!
0"
0#
0$
#90000
0!
1"
#100000
0!
0"
1#
#110000
1!
1"
#120000
0!
0"
0#
1$
#130000
1!
1"
#140000
0"
1#
#150000
1"
#160000
1!
0"
0#
0$
#170000
0!
1"
#180000
0!
0"
1#
#190000
1!
1"
#200000
0!
0"
0#
1$
